dbmsbenchmarker/__init__.py
dbmsbenchmarker/__version__.py
dbmsbenchmarker/benchmarker.py
dbmsbenchmarker/evaluator.py
dbmsbenchmarker/inspector.py
dbmsbenchmarker/layout.py
dbmsbenchmarker/monitor.py
dbmsbenchmarker/parameter.py
dbmsbenchmarker/reporter.py
dbmsbenchmarker/tools.py
dbmsbenchmarker/scripts/__init__.py
dbmsbenchmarker/scripts/cli.py
dbmsbenchmarker/scripts/dashboardcli.py
dbmsbenchmarker/scripts/inspect.py
dbmsbenchmarker/scripts/assets/styles.css
dbmsbenchmarker/scripts/assets/icons/check_box-24px.svg
dbmsbenchmarker/scripts/assets/icons/check_box_outline_blank-24px.svg
dbmsbenchmarker/scripts/assets/icons/chevron_down.svg
dbmsbenchmarker/scripts/assets/icons/chevron_up.svg
dbmsbenchmarker/scripts/assets/icons/clear-black-24dp.svg
dbmsbenchmarker/scripts/assets/icons/get_app-black-24dp.svg
dbmsbenchmarker/scripts/assets/icons/info-24px.svg
dbmsbenchmarker/scripts/assets/icons/radio_button_unchecked-24px.svg
dbmsbenchmarker/scripts/assets/icons/tune-black-24dp.svg
dbmsbenchmarker-0.14.16.dist-info/licenses/LICENSE
dbmsbenchmarker-0.14.16.dist-info/METADATA
dbmsbenchmarker-0.14.16.dist-info/WHEEL
dbmsbenchmarker-0.14.16.dist-info/entry_points.txt
dbmsbenchmarker-0.14.16.dist-info/top_level.txt
dbmsbenchmarker-0.14.16.dist-info/RECORD
