Metadata-Version: 2.4
Name: dbmsbenchmarker
Version: 0.14.16
Summary: DBMS-Benchmarker is a Python-based application-level blackbox benchmark tool for Database Management Systems (DBMS). It connects to a given list of DBMS (via JDBC) and runs a given list of parametrized and randomized (SQL) benchmark queries. Evaluations are available via Python interface, in reports and at an interactive multi-dimensional dashboard.
Author-email: "Patrick K. Erdelt" <patrick.erdelt@bht-berlin.de>
License: GNU Affero General Public License v3
Project-URL: Homepage, https://github.com/Beuth-Erdelt/DBMS-Benchmarker
Project-URL: Repository, https://github.com/Beuth-Erdelt/DBMS-Benchmarker
Classifier: Programming Language :: Python :: 3
Classifier: License :: OSI Approved :: GNU Affero General Public License v3
Classifier: Operating System :: OS Independent
Requires-Python: >=3.6
License-File: LICENSE
Requires-Dist: JayDeBeApi>=1.1.1
Requires-Dist: matplotlib>=3.1.1
Requires-Dist: numpy>=1.22.2
Requires-Dist: pandas>=2.1
Requires-Dist: tabulate>=0.8.2
Requires-Dist: tqdm>=4.28.1
Requires-Dist: requests>=2.32.0
Requires-Dist: JPype1>=1.2.0
Requires-Dist: scipy>=1.4.1
Requires-Dist: colour>=0.1.5
Requires-Dist: Brotli>=1.0.7
Requires-Dist: certifi>=2023.7.22
Requires-Dist: chardet>=3.0.4
Requires-Dist: click>=6.7
Requires-Dist: colour>=0.1.5
Requires-Dist: cycler>=0.10.0
Requires-Dist: dash>=2.15.0
Requires-Dist: dash-auth
Requires-Dist: dash-core-components
Requires-Dist: dash-daq
Requires-Dist: dash-html-components
Requires-Dist: dash-renderer
Requires-Dist: dash-table
Requires-Dist: Flask==2.2.5
Requires-Dist: Flask-Caching
Requires-Dist: future>=0.18.2
Requires-Dist: idna>=2.9
Requires-Dist: itsdangerous>=1.1.0
Requires-Dist: kiwisolver>=1.2.0
Requires-Dist: MarkupSafe>=1.1.1
Requires-Dist: plotly>=4.8.1
Requires-Dist: pyparsing>=2.4.7
Requires-Dist: python-dateutil>=2.8.1
Requires-Dist: pytz>=2020.1
Requires-Dist: retrying>=1.3.3
Requires-Dist: six>=1.14.0
Requires-Dist: urllib3>=2.2.2
Requires-Dist: uuid>=1.30
Requires-Dist: Werkzeug>=3.0.6
Requires-Dist: mistune>=2.0.3
Requires-Dist: pillow>=10.0.1
Requires-Dist: setuptools>=78.1.1
Requires-Dist: fonttools>=4.43.0
Requires-Dist: jinja2>=3.1.3
Requires-Dist: Bottleneck>=1.4.0
Requires-Dist: zipp>=3.19.1
Dynamic: license-file
